chillboss/__init__.py
chillboss/__main__.py
chillboss/loggers.py
chillboss/mouse.py
chillboss-0.4.1.dist-info/entry_points.txt
chillboss-0.4.1.dist-info/LICENSE
chillboss-0.4.1.dist-info/WHEEL
chillboss-0.4.1.dist-info/METADATA
chillboss-0.4.1.dist-info/RECORD
