Metadata-Version: 2.1
Name: chillboss
Version: 0.4.1
Summary: Let's chill, Pointer moves forever.
Home-page: https://naveenkumarreddy8.github.io/ChillBoss/
License: MIT
Author: NaveenKumarReddy8
Author-email: mr.naveen8@gmail.com
Requires-Python: >=3.6,<4.0
Classifier: License :: OSI Approved :: MIT License
Classifier: Programming Language :: Python :: 3
Classifier: Programming Language :: Python :: 3.10
Classifier: Programming Language :: Python :: 3.6
Classifier: Programming Language :: Python :: 3.7
Classifier: Programming Language :: Python :: 3.8
Classifier: Programming Language :: Python :: 3.9
Requires-Dist: PyAutogui (>=0.9.50,<0.10.0)
Requires-Dist: click (>=7.1.2,<9.0.0)
Requires-Dist: colorama (>=0.4.4,<0.5.0)
Requires-Dist: emoji (>=1.2.0,<2.0.0)
Requires-Dist: importlib-metadata (>=4.0.1,<5.0.0)
Requires-Dist: pyfiglet (>=0.8.post1,<0.9)
Project-URL: Repository, https://github.com/NaveenKumarReddy8/ChillBoss
